[
  {
    "account_id": "all_weather",
    "avg_cost_krw": 39073.8406,
    "company": "KODEX 200",
    "currency": "KRW",
    "first_buy_date": "2021-01-04",
    "holding_days": 1974,
    "last_close_krw": 141395.0,
    "last_close_native": 141395.0,
    "market_value_krw": 62779380.0,
    "qty": 444,
    "symbol": "069500.KS",
    "unrealized_pnl_krw": 45430594.7587,
    "unrealized_return": 2.6186614325288513
  },
  {
    "account_id": "all_weather",
    "avg_cost_krw": 594228.4292,
    "company": "NASDAQ-100",
    "currency": "USD",
    "first_buy_date": "2021-01-04",
    "holding_days": 1974,
    "last_close_krw": 1119190.3015,
    "last_close_native": 717.9635665236781,
    "market_value_krw": 61555466.5825,
    "qty": 55,
    "symbol": "QQQ",
    "unrealized_pnl_krw": 28872902.9765,
    "unrealized_return": 0.8834344614019016
  },
  {
    "account_id": "all_weather",
    "avg_cost_krw": 350485.7385,
    "company": "Gold",
    "currency": "USD",
    "first_buy_date": "2021-01-04",
    "holding_days": 1974,
    "last_close_krw": 619703.0191,
    "last_close_native": 397.54114128956917,
    "market_value_krw": 58252083.7954,
    "qty": 94,
    "symbol": "GLD",
    "unrealized_pnl_krw": 25306424.375,
    "unrealized_return": 0.7681262060824197
  },
  {
    "account_id": "all_weather",
    "avg_cost_krw": 707918.4065,
    "company": "S&P 500",
    "currency": "USD",
    "first_buy_date": "2021-01-04",
    "holding_days": 1974,
    "last_close_krw": 1142998.3546,
    "last_close_native": 733.2364961521351,
    "market_value_krw": 57149917.73,
    "qty": 50,
    "symbol": "SPY",
    "unrealized_pnl_krw": 21753997.4048,
    "unrealized_return": 0.6145905292264779
  },
  {
    "account_id": "benchmark_gld",
    "avg_cost_krw": 279285.4914,
    "company": "Gold",
    "currency": "USD",
    "first_buy_date": "2021-01-04",
    "holding_days": 1974,
    "last_close_krw": 619703.0191,
    "last_close_native": 397.54114128956917,
    "market_value_krw": 229909820.0861,
    "qty": 371,
    "symbol": "GLD",
    "unrealized_pnl_krw": 126294902.754,
    "unrealized_return": 1.2188872611805142
  },
  {
    "account_id": "benchmark_kodex200",
    "avg_cost_krw": 39393.9504,
    "company": "KODEX 200",
    "currency": "KRW",
    "first_buy_date": "2021-01-04",
    "holding_days": 1974,
    "last_close_krw": 141395.0,
    "last_close_native": 141395.0,
    "market_value_krw": 372858615.0,
    "qty": 2637,
    "symbol": "069500.KS",
    "unrealized_pnl_krw": 268976767.8799,
    "unrealized_return": 2.5892566895245923
  },
  {
    "account_id": "benchmark_qqq",
    "avg_cost_krw": 522945.7318,
    "company": "NASDAQ-100",
    "currency": "USD",
    "first_buy_date": "2021-01-04",
    "holding_days": 1974,
    "last_close_krw": 1119190.3015,
    "last_close_native": 717.9635665236781,
    "market_value_krw": 221599679.69700003,
    "qty": 198,
    "symbol": "QQQ",
    "unrealized_pnl_krw": 118056424.7999,
    "unrealized_return": 1.1401652856936084
  },
  {
    "account_id": "benchmark_spy",
    "avg_cost_krw": 629609.8243,
    "company": "S&P 500",
    "currency": "USD",
    "first_buy_date": "2021-01-04",
    "holding_days": 1974,
    "last_close_krw": 1142998.3546,
    "last_close_native": 733.2364961521351,
    "market_value_krw": 188594728.509,
    "qty": 165,
    "symbol": "SPY",
    "unrealized_pnl_krw": 84709107.4934,
    "unrealized_return": 0.8154074324853258
  },
  {
    "account_id": "pit_fresh_top5",
    "avg_cost_krw": 1127437.5678,
    "company": "Lumentum Holdings Inc",
    "currency": "USD",
    "first_buy_date": "2026-03-02",
    "holding_days": 91,
    "last_close_krw": 1344995.9815,
    "last_close_native": 863.6599731445312,
    "market_value_krw": 52454843.2785,
    "qty": 39,
    "symbol": "LITE",
    "unrealized_pnl_krw": 8484778.1334,
    "unrealized_return": 0.19296714950214722
  },
  {
    "account_id": "pit_fresh_top5",
    "avg_cost_krw": 316705.7487,
    "company": "로보티즈",
    "currency": "KRW",
    "first_buy_date": "2026-05-01",
    "holding_days": 31,
    "last_close_krw": 402500.0,
    "last_close_native": 320500.0,
    "market_value_krw": 51922500.0,
    "qty": 129,
    "symbol": "108490.KQ",
    "unrealized_pnl_krw": 11067458.4129,
    "unrealized_return": 0.270895781501171
  },
  {
    "account_id": "pit_fresh_top5",
    "avg_cost_krw": 38274.8654,
    "company": "코스텍시스",
    "currency": "KRW",
    "first_buy_date": "2026-06-01",
    "holding_days": 0,
    "last_close_krw": 38250.0,
    "last_close_native": 36400.0,
    "market_value_krw": 51790500.0,
    "qty": 1354,
    "symbol": "355150.KS",
    "unrealized_pnl_krw": -33667.7093,
    "unrealized_return": -0.0006496534929683051
  },
  {
    "account_id": "pit_fresh_top5",
    "avg_cost_krw": 2204432.1152,
    "company": "두산",
    "currency": "KRW",
    "first_buy_date": "2026-06-01",
    "holding_days": 0,
    "last_close_krw": 2203000.0,
    "last_close_native": 1740000.0,
    "market_value_krw": 50669000.0,
    "qty": 23,
    "symbol": "000150.KS",
    "unrealized_pnl_krw": -32938.6502,
    "unrealized_return": -0.0006496526657024937
  },
  {
    "account_id": "pit_fresh_top5",
    "avg_cost_krw": 2738799.3664,
    "company": "Comfort Systems USA, Inc.",
    "currency": "USD",
    "first_buy_date": "2026-06-01",
    "holding_days": 0,
    "last_close_krw": 2737020.098,
    "last_close_native": 1843.93994140625,
    "market_value_krw": 49266361.764000006,
    "qty": 18,
    "symbol": "FIX",
    "unrealized_pnl_krw": -32026.8301,
    "unrealized_return": -0.0006496526988534201
  },
  {
    "account_id": "pit_momentum_1m3m_top5",
    "avg_cost_krw": 1597037.5197,
    "company": "두산",
    "currency": "KRW",
    "first_buy_date": "2026-05-01",
    "holding_days": 31,
    "last_close_krw": 2203000.0,
    "last_close_native": 1740000.0,
    "market_value_krw": 44060000.0,
    "qty": 20,
    "symbol": "000150.KS",
    "unrealized_pnl_krw": 12119249.606,
    "unrealized_return": 0.37942908217574534
  },
  {
    "account_id": "pit_momentum_1m3m_top5",
    "avg_cost_krw": 97876.9148,
    "company": "Aixtron SE",
    "currency": "EUR",
    "first_buy_date": "2026-06-01",
    "holding_days": 0,
    "last_close_krw": 97813.3288,
    "last_close_native": 54.639999389648445,
    "market_value_krw": 43135678.0008,
    "qty": 441,
    "symbol": "AIXA.DE",
    "unrealized_pnl_krw": -28041.4259,
    "unrealized_return": -0.0006496526798982494
  },
  {
    "account_id": "pit_momentum_1m3m_top5",
    "avg_cost_krw": 402761.6552,
    "company": "로보티즈",
    "currency": "KRW",
    "first_buy_date": "2026-06-01",
    "holding_days": 0,
    "last_close_krw": 402500.0,
    "last_close_native": 320500.0,
    "market_value_krw": 43067500.0,
    "qty": 107,
    "symbol": "108490.KQ",
    "unrealized_pnl_krw": -27997.1051,
    "unrealized_return": -0.0006496527080515069
  },
  {
    "account_id": "pit_momentum_1m3m_top5",
    "avg_cost_krw": 761494.7071,
    "company": "현대모비스",
    "currency": "KRW",
    "first_buy_date": "2026-06-01",
    "holding_days": 0,
    "last_close_krw": 761000.0,
    "last_close_native": 697000.0,
    "market_value_krw": 42616000.0,
    "qty": 56,
    "symbol": "012330.KS",
    "unrealized_pnl_krw": -27703.5962,
    "unrealized_return": -0.0006496527098448501
  },
  {
    "account_id": "pit_momentum_1m3m_top5",
    "avg_cost_krw": 1288593.9606,
    "company": "Sterling Infrastructure Inc",
    "currency": "USD",
    "first_buy_date": "2026-06-01",
    "holding_days": 0,
    "last_close_krw": 1287756.8221,
    "last_close_native": 882.4299926757812,
    "market_value_krw": 42495975.1293,
    "qty": 33,
    "symbol": "STRL",
    "unrealized_pnl_krw": -27625.571,
    "unrealized_return": -0.000649652664529321
  },
  {
    "account_id": "pit_momentum_3m6m_top5",
    "avg_cost_krw": 1597037.5197,
    "company": "두산",
    "currency": "KRW",
    "first_buy_date": "2026-05-01",
    "holding_days": 31,
    "last_close_krw": 2203000.0,
    "last_close_native": 1740000.0,
    "market_value_krw": 46263000.0,
    "qty": 21,
    "symbol": "000150.KS",
    "unrealized_pnl_krw": 12725212.0863,
    "unrealized_return": 0.37942908217574534
  },
  {
    "account_id": "pit_momentum_3m6m_top5",
    "avg_cost_krw": 56678.0247,
    "company": "비츠로셀",
    "currency": "KRW",
    "first_buy_date": "2026-05-01",
    "holding_days": 31,
    "last_close_krw": 52000.0,
    "last_close_native": 48650.0,
    "market_value_krw": 44928000.0,
    "qty": 864,
    "symbol": "082920.KS",
    "unrealized_pnl_krw": -4041813.3703,
    "unrealized_return": -0.08253683371573117
  },
  {
    "account_id": "pit_momentum_3m6m_top5",
    "avg_cost_krw": 761494.7071,
    "company": "현대모비스",
    "currency": "KRW",
    "first_buy_date": "2026-06-01",
    "holding_days": 0,
    "last_close_krw": 761000.0,
    "last_close_native": 697000.0,
    "market_value_krw": 44899000.0,
    "qty": 59,
    "symbol": "012330.KS",
    "unrealized_pnl_krw": -29187.7174,
    "unrealized_return": -0.0006496527098448501
  },
  {
    "account_id": "pit_momentum_3m6m_top5",
    "avg_cost_krw": 97876.9148,
    "company": "Aixtron SE",
    "currency": "EUR",
    "first_buy_date": "2026-06-01",
    "holding_days": 0,
    "last_close_krw": 97813.3288,
    "last_close_native": 54.639999389648445,
    "market_value_krw": 44896317.9192,
    "qty": 459,
    "symbol": "AIXA.DE",
    "unrealized_pnl_krw": -29185.9739,
    "unrealized_return": -0.0006496526798982494
  },
  {
    "account_id": "pit_momentum_3m6m_top5",
    "avg_cost_krw": 1288593.9606,
    "company": "Sterling Infrastructure Inc",
    "currency": "USD",
    "first_buy_date": "2026-06-01",
    "holding_days": 0,
    "last_close_krw": 1287756.8221,
    "last_close_native": 882.4299926757812,
    "market_value_krw": 42495975.1293,
    "qty": 33,
    "symbol": "STRL",
    "unrealized_pnl_krw": -27625.571,
    "unrealized_return": -0.000649652664529321
  },
  {
    "account_id": "pit_momentum_6m12m_top5",
    "avg_cost_krw": 1597037.5197,
    "company": "두산",
    "currency": "KRW",
    "first_buy_date": "2026-05-01",
    "holding_days": 31,
    "last_close_krw": 2203000.0,
    "last_close_native": 1740000.0,
    "market_value_krw": 48466000.0,
    "qty": 22,
    "symbol": "000150.KS",
    "unrealized_pnl_krw": 13331174.5666,
    "unrealized_return": 0.37942908217574534
  },
  {
    "account_id": "pit_momentum_6m12m_top5",
    "avg_cost_krw": 761494.7071,
    "company": "현대모비스",
    "currency": "KRW",
    "first_buy_date": "2026-06-01",
    "holding_days": 0,
    "last_close_krw": 761000.0,
    "last_close_native": 697000.0,
    "market_value_krw": 47182000.0,
    "qty": 62,
    "symbol": "012330.KS",
    "unrealized_pnl_krw": -30671.8387,
    "unrealized_return": -0.0006496527098448501
  },
  {
    "account_id": "pit_momentum_6m12m_top5",
    "avg_cost_krw": 97876.9148,
    "company": "Aixtron SE",
    "currency": "EUR",
    "first_buy_date": "2026-06-01",
    "holding_days": 0,
    "last_close_krw": 97813.3288,
    "last_close_native": 54.639999389648445,
    "market_value_krw": 47146024.4816,
    "qty": 482,
    "symbol": "AIXA.DE",
    "unrealized_pnl_krw": -30648.4519,
    "unrealized_return": -0.0006496526798982494
  },
  {
    "account_id": "pit_momentum_6m12m_top5",
    "avg_cost_krw": 402761.6552,
    "company": "로보티즈",
    "currency": "KRW",
    "first_buy_date": "2026-06-01",
    "holding_days": 0,
    "last_close_krw": 402500.0,
    "last_close_native": 320500.0,
    "market_value_krw": 47092500.0,
    "qty": 117,
    "symbol": "108490.KQ",
    "unrealized_pnl_krw": -30613.6569,
    "unrealized_return": -0.0006496527080515069
  },
  {
    "account_id": "pit_momentum_6m12m_top5",
    "avg_cost_krw": 1288593.9606,
    "company": "Sterling Infrastructure Inc",
    "currency": "USD",
    "first_buy_date": "2026-06-01",
    "holding_days": 0,
    "last_close_krw": 1287756.8221,
    "last_close_native": 882.4299926757812,
    "market_value_krw": 45071488.7735,
    "qty": 35,
    "symbol": "STRL",
    "unrealized_pnl_krw": -29299.8481,
    "unrealized_return": -0.000649652664529321
  },
  {
    "account_id": "pit_momentum_top5",
    "avg_cost_krw": 1597037.5197,
    "company": "두산",
    "currency": "KRW",
    "first_buy_date": "2026-05-01",
    "holding_days": 31,
    "last_close_krw": 2203000.0,
    "last_close_native": 1740000.0,
    "market_value_krw": 68293000.0,
    "qty": 31,
    "symbol": "000150.KS",
    "unrealized_pnl_krw": 18784836.8893,
    "unrealized_return": 0.37942908217574534
  },
  {
    "account_id": "pit_momentum_top5",
    "avg_cost_krw": 56688.9,
    "company": "비츠로셀",
    "currency": "KRW",
    "first_buy_date": "2026-05-01",
    "holding_days": 31,
    "last_close_krw": 52000.0,
    "last_close_native": 48650.0,
    "market_value_krw": 66508000.0,
    "qty": 1279,
    "symbol": "082920.KS",
    "unrealized_pnl_krw": -5997103.1344,
    "unrealized_return": -0.08271284149101499
  },
  {
    "account_id": "pit_momentum_top5",
    "avg_cost_krw": 97876.9148,
    "company": "Aixtron SE",
    "currency": "EUR",
    "first_buy_date": "2026-06-01",
    "holding_days": 0,
    "last_close_krw": 97813.3288,
    "last_close_native": 54.639999389648445,
    "market_value_krw": 66415250.2552,
    "qty": 679,
    "symbol": "AIXA.DE",
    "unrealized_pnl_krw": -43174.8938,
    "unrealized_return": -0.0006496526798982494
  },
  {
    "account_id": "pit_momentum_top5",
    "avg_cost_krw": 761494.7071,
    "company": "현대모비스",
    "currency": "KRW",
    "first_buy_date": "2026-06-01",
    "holding_days": 0,
    "last_close_krw": 761000.0,
    "last_close_native": 697000.0,
    "market_value_krw": 66207000.0,
    "qty": 87,
    "symbol": "012330.KS",
    "unrealized_pnl_krw": -43039.5155,
    "unrealized_return": -0.0006496527098448501
  },
  {
    "account_id": "pit_momentum_top5",
    "avg_cost_krw": 1288593.9606,
    "company": "Sterling Infrastructure Inc",
    "currency": "USD",
    "first_buy_date": "2026-06-01",
    "holding_days": 0,
    "last_close_krw": 1287756.8221,
    "last_close_native": 882.4299926757812,
    "market_value_krw": 64387841.105,
    "qty": 50,
    "symbol": "STRL",
    "unrealized_pnl_krw": -41856.9258,
    "unrealized_return": -0.000649652664529321
  },
  {
    "account_id": "pit_mtt_low100_top5",
    "avg_cost_krw": 1597037.5197,
    "company": "두산",
    "currency": "KRW",
    "first_buy_date": "2026-05-01",
    "holding_days": 31,
    "last_close_krw": 2203000.0,
    "last_close_native": 1740000.0,
    "market_value_krw": 48466000.0,
    "qty": 22,
    "symbol": "000150.KS",
    "unrealized_pnl_krw": 13331174.5666,
    "unrealized_return": 0.37942908217574534
  },
  {
    "account_id": "pit_mtt_low100_top5",
    "avg_cost_krw": 56682.4496,
    "company": "비츠로셀",
    "currency": "KRW",
    "first_buy_date": "2026-05-01",
    "holding_days": 31,
    "last_close_krw": 52000.0,
    "last_close_native": 48650.0,
    "market_value_krw": 46956000.0,
    "qty": 903,
    "symbol": "082920.KS",
    "unrealized_pnl_krw": -4228251.9863,
    "unrealized_return": -0.0826084552280888
  },
  {
    "account_id": "pit_mtt_low100_top5",
    "avg_cost_krw": 97876.9148,
    "company": "Aixtron SE",
    "currency": "EUR",
    "first_buy_date": "2026-06-01",
    "holding_days": 0,
    "last_close_krw": 97813.3288,
    "last_close_native": 54.639999389648445,
    "market_value_krw": 46950397.824,
    "qty": 480,
    "symbol": "AIXA.DE",
    "unrealized_pnl_krw": -30521.2799,
    "unrealized_return": -0.0006496526798982494
  },
  {
    "account_id": "pit_mtt_low100_top5",
    "avg_cost_krw": 761494.7071,
    "company": "현대모비스",
    "currency": "KRW",
    "first_buy_date": "2026-06-01",
    "holding_days": 0,
    "last_close_krw": 761000.0,
    "last_close_native": 697000.0,
    "market_value_krw": 46421000.0,
    "qty": 61,
    "symbol": "012330.KS",
    "unrealized_pnl_krw": -30177.1316,
    "unrealized_return": -0.0006496527098448501
  },
  {
    "account_id": "pit_mtt_low100_top5",
    "avg_cost_krw": 1288593.9606,
    "company": "Sterling Infrastructure Inc",
    "currency": "USD",
    "first_buy_date": "2026-06-01",
    "holding_days": 0,
    "last_close_krw": 1287756.8221,
    "last_close_native": 882.4299926757812,
    "market_value_krw": 45071488.7735,
    "qty": 35,
    "symbol": "STRL",
    "unrealized_pnl_krw": -29299.8481,
    "unrealized_return": -0.000649652664529321
  },
  {
    "account_id": "pit_mtt_low300_top5",
    "avg_cost_krw": 1597037.5197,
    "company": "두산",
    "currency": "KRW",
    "first_buy_date": "2026-05-01",
    "holding_days": 31,
    "last_close_krw": 2203000.0,
    "last_close_native": 1740000.0,
    "market_value_krw": 61684000.0,
    "qty": 28,
    "symbol": "000150.KS",
    "unrealized_pnl_krw": 16966949.4484,
    "unrealized_return": 0.37942908217574534
  },
  {
    "account_id": "pit_mtt_low300_top5",
    "avg_cost_krw": 56410.5678,
    "company": "비츠로셀",
    "currency": "KRW",
    "first_buy_date": "2026-05-01",
    "holding_days": 31,
    "last_close_krw": 52000.0,
    "last_close_native": 48650.0,
    "market_value_krw": 60216000.0,
    "qty": 1158,
    "symbol": "082920.KS",
    "unrealized_pnl_krw": -5107437.5461,
    "unrealized_return": -0.0781869066738945
  },
  {
    "account_id": "pit_mtt_low300_top5",
    "avg_cost_krw": 97876.9148,
    "company": "Aixtron SE",
    "currency": "EUR",
    "first_buy_date": "2026-06-01",
    "holding_days": 0,
    "last_close_krw": 97813.3288,
    "last_close_native": 54.639999389648445,
    "market_value_krw": 60155197.212000005,
    "qty": 615,
    "symbol": "AIXA.DE",
    "unrealized_pnl_krw": -39105.3898,
    "unrealized_return": -0.0006496526798982494
  },
  {
    "account_id": "pit_mtt_low300_top5",
    "avg_cost_krw": 402761.6552,
    "company": "로보티즈",
    "currency": "KRW",
    "first_buy_date": "2026-06-01",
    "holding_days": 0,
    "last_close_krw": 402500.0,
    "last_close_native": 320500.0,
    "market_value_krw": 59972500.0,
    "qty": 149,
    "symbol": "108490.KQ",
    "unrealized_pnl_krw": -38986.6229,
    "unrealized_return": -0.0006496527080515069
  },
  {
    "account_id": "pit_mtt_low300_top5",
    "avg_cost_krw": 1288593.9606,
    "company": "Sterling Infrastructure Inc",
    "currency": "USD",
    "first_buy_date": "2026-06-01",
    "holding_days": 0,
    "last_close_krw": 1287756.8221,
    "last_close_native": 882.4299926757812,
    "market_value_krw": 57949056.9945,
    "qty": 45,
    "symbol": "STRL",
    "unrealized_pnl_krw": -37671.2332,
    "unrealized_return": -0.000649652664529321
  },
  {
    "account_id": "pit_mtt_rs70_top5",
    "avg_cost_krw": 1597037.5197,
    "company": "두산",
    "currency": "KRW",
    "first_buy_date": "2026-05-01",
    "holding_days": 31,
    "last_close_krw": 2203000.0,
    "last_close_native": 1740000.0,
    "market_value_krw": 44060000.0,
    "qty": 20,
    "symbol": "000150.KS",
    "unrealized_pnl_krw": 12119249.606,
    "unrealized_return": 0.37942908217574534
  },
  {
    "account_id": "pit_mtt_rs70_top5",
    "avg_cost_krw": 97876.9148,
    "company": "Aixtron SE",
    "currency": "EUR",
    "first_buy_date": "2026-06-01",
    "holding_days": 0,
    "last_close_krw": 97813.3288,
    "last_close_native": 54.639999389648445,
    "market_value_krw": 41864104.7264,
    "qty": 428,
    "symbol": "AIXA.DE",
    "unrealized_pnl_krw": -27214.8079,
    "unrealized_return": -0.0006496526798982494
  },
  {
    "account_id": "pit_mtt_rs70_top5",
    "avg_cost_krw": 402761.6552,
    "company": "로보티즈",
    "currency": "KRW",
    "first_buy_date": "2026-06-01",
    "holding_days": 0,
    "last_close_krw": 402500.0,
    "last_close_native": 320500.0,
    "market_value_krw": 41860000.0,
    "qty": 104,
    "symbol": "108490.KQ",
    "unrealized_pnl_krw": -27212.1395,
    "unrealized_return": -0.0006496527080515069
  },
  {
    "account_id": "pit_mtt_rs70_top5",
    "avg_cost_krw": 761494.7071,
    "company": "현대모비스",
    "currency": "KRW",
    "first_buy_date": "2026-06-01",
    "holding_days": 0,
    "last_close_krw": 761000.0,
    "last_close_native": 697000.0,
    "market_value_krw": 41855000.0,
    "qty": 55,
    "symbol": "012330.KS",
    "unrealized_pnl_krw": -27208.8891,
    "unrealized_return": -0.0006496527098448501
  },
  {
    "account_id": "pit_mtt_rs70_top5",
    "avg_cost_krw": 1288593.9606,
    "company": "Sterling Infrastructure Inc",
    "currency": "USD",
    "first_buy_date": "2026-06-01",
    "holding_days": 0,
    "last_close_krw": 1287756.8221,
    "last_close_native": 882.4299926757812,
    "market_value_krw": 38632704.663,
    "qty": 30,
    "symbol": "STRL",
    "unrealized_pnl_krw": -25114.1555,
    "unrealized_return": -0.000649652664529321
  },
  {
    "account_id": "pit_mtt_rs80_top5",
    "avg_cost_krw": 1597037.5197,
    "company": "두산",
    "currency": "KRW",
    "first_buy_date": "2026-05-01",
    "holding_days": 31,
    "last_close_krw": 2203000.0,
    "last_close_native": 1740000.0,
    "market_value_krw": 48466000.0,
    "qty": 22,
    "symbol": "000150.KS",
    "unrealized_pnl_krw": 13331174.5666,
    "unrealized_return": 0.37942908217574534
  },
  {
    "account_id": "pit_mtt_rs80_top5",
    "avg_cost_krw": 56675.3735,
    "company": "비츠로셀",
    "currency": "KRW",
    "first_buy_date": "2026-05-01",
    "holding_days": 31,
    "last_close_krw": 52000.0,
    "last_close_native": 48650.0,
    "market_value_krw": 47476000.0,
    "qty": 913,
    "symbol": "082920.KS",
    "unrealized_pnl_krw": -4268616.0283,
    "unrealized_return": -0.08249391598627931
  },
  {
    "account_id": "pit_mtt_rs80_top5",
    "avg_cost_krw": 97876.9148,
    "company": "Aixtron SE",
    "currency": "EUR",
    "first_buy_date": "2026-06-01",
    "holding_days": 0,
    "last_close_krw": 97813.3288,
    "last_close_native": 54.639999389648445,
    "market_value_krw": 47439464.468,
    "qty": 485,
    "symbol": "AIXA.DE",
    "unrealized_pnl_krw": -30839.2099,
    "unrealized_return": -0.0006496526798982494
  },
  {
    "account_id": "pit_mtt_rs80_top5",
    "avg_cost_krw": 761494.7071,
    "company": "현대모비스",
    "currency": "KRW",
    "first_buy_date": "2026-06-01",
    "holding_days": 0,
    "last_close_krw": 761000.0,
    "last_close_native": 697000.0,
    "market_value_krw": 47182000.0,
    "qty": 62,
    "symbol": "012330.KS",
    "unrealized_pnl_krw": -30671.8387,
    "unrealized_return": -0.0006496527098448501
  },
  {
    "account_id": "pit_mtt_rs80_top5",
    "avg_cost_krw": 1288593.9606,
    "company": "Sterling Infrastructure Inc",
    "currency": "USD",
    "first_buy_date": "2026-06-01",
    "holding_days": 0,
    "last_close_krw": 1287756.8221,
    "last_close_native": 882.4299926757812,
    "market_value_krw": 46359245.5956,
    "qty": 36,
    "symbol": "STRL",
    "unrealized_pnl_krw": -30136.9866,
    "unrealized_return": -0.000649652664529321
  },
  {
    "account_id": "pit_mtt_rs90_top5",
    "avg_cost_krw": 1597037.5197,
    "company": "두산",
    "currency": "KRW",
    "first_buy_date": "2026-05-01",
    "holding_days": 31,
    "last_close_krw": 2203000.0,
    "last_close_native": 1740000.0,
    "market_value_krw": 50669000.0,
    "qty": 23,
    "symbol": "000150.KS",
    "unrealized_pnl_krw": 13937137.0469,
    "unrealized_return": 0.37942908217574534
  },
  {
    "account_id": "pit_mtt_rs90_top5",
    "avg_cost_krw": 97876.9148,
    "company": "Aixtron SE",
    "currency": "EUR",
    "first_buy_date": "2026-06-01",
    "holding_days": 0,
    "last_close_krw": 97813.3288,
    "last_close_native": 54.639999389648445,
    "market_value_krw": 48515411.084800005,
    "qty": 496,
    "symbol": "AIXA.DE",
    "unrealized_pnl_krw": -31538.6558,
    "unrealized_return": -0.0006496526798982494
  },
  {
    "account_id": "pit_mtt_rs90_top5",
    "avg_cost_krw": 106369.103,
    "company": "티엘비",
    "currency": "KRW",
    "first_buy_date": "2026-06-01",
    "holding_days": 0,
    "last_close_krw": 106300.0,
    "last_close_native": 106700.0,
    "market_value_krw": 48472800.0,
    "qty": 456,
    "symbol": "356860.KQ",
    "unrealized_pnl_krw": -31510.9555,
    "unrealized_return": -0.0006496529354017566
  },
  {
    "account_id": "pit_mtt_rs90_top5",
    "avg_cost_krw": 402761.6552,
    "company": "로보티즈",
    "currency": "KRW",
    "first_buy_date": "2026-06-01",
    "holding_days": 0,
    "last_close_krw": 402500.0,
    "last_close_native": 320500.0,
    "market_value_krw": 48300000.0,
    "qty": 120,
    "symbol": "108490.KQ",
    "unrealized_pnl_krw": -31398.6225,
    "unrealized_return": -0.0006496527080515069
  },
  {
    "account_id": "pit_mtt_rs90_top5",
    "avg_cost_krw": 1288593.9606,
    "company": "Sterling Infrastructure Inc",
    "currency": "USD",
    "first_buy_date": "2026-06-01",
    "holding_days": 0,
    "last_close_krw": 1287756.8221,
    "last_close_native": 882.4299926757812,
    "market_value_krw": 46359245.5956,
    "qty": 36,
    "symbol": "STRL",
    "unrealized_pnl_krw": -30136.9866,
    "unrealized_return": -0.000649652664529321
  },
  {
    "account_id": "pit_score_top10",
    "avg_cost_krw": 1286835.9964,
    "company": "SK하이닉스",
    "currency": "KRW",
    "first_buy_date": "2026-05-01",
    "holding_days": 31,
    "last_close_krw": 2363000.0,
    "last_close_native": 2070000.0,
    "market_value_krw": 23630000.0,
    "qty": 10,
    "symbol": "000660.KS",
    "unrealized_pnl_krw": 10761640.0355,
    "unrealized_return": 0.8362868357822073
  },
  {
    "account_id": "pit_score_top10",
    "avg_cost_krw": 56136.4692,
    "company": "주성엔지니어링",
    "currency": "KRW",
    "first_buy_date": "2026-03-02",
    "holding_days": 91,
    "last_close_krw": 185500.0,
    "last_close_native": 210000.0,
    "market_value_krw": 22816500.0,
    "qty": 123,
    "symbol": "036930.KQ",
    "unrealized_pnl_krw": 15911714.2875,
    "unrealized_return": 2.30444722732936
  },
  {
    "account_id": "pit_score_top10",
    "avg_cost_krw": 3638.4572,
    "company": "지트리비앤티",
    "currency": "KRW",
    "first_buy_date": "2021-01-04",
    "holding_days": 1974,
    "last_close_krw": 2600.0,
    "last_close_native": 2655.0,
    "market_value_krw": 22687600.0,
    "qty": 8726,
    "symbol": "115450.KS",
    "unrealized_pnl_krw": -9061577.6252,
    "unrealized_return": -0.2854114100888695
  },
  {
    "account_id": "pit_score_top10",
    "avg_cost_krw": 32069.1823,
    "company": "SNT에너지",
    "currency": "KRW",
    "first_buy_date": "2023-01-02",
    "holding_days": 1246,
    "last_close_krw": 36800.0,
    "last_close_native": 33900.0,
    "market_value_krw": 22668800.0,
    "qty": 616,
    "symbol": "100840.KQ",
    "unrealized_pnl_krw": 2914183.6946,
    "unrealized_return": 0.14751912461453687
  },
  {
    "account_id": "pit_score_top10",
    "avg_cost_krw": 111172.2233,
    "company": "파두",
    "currency": "KRW",
    "first_buy_date": "2026-06-01",
    "holding_days": 0,
    "last_close_krw": 111100.0,
    "last_close_native": 109800.0,
    "market_value_krw": 22664400.0,
    "qty": 204,
    "symbol": "440110.KQ",
    "unrealized_pnl_krw": -14733.5598,
    "unrealized_return": -0.0006496523848866786
  },
  {
    "account_id": "pit_score_top10",
    "avg_cost_krw": 106369.103,
    "company": "티엘비",
    "currency": "KRW",
    "first_buy_date": "2026-06-01",
    "holding_days": 0,
    "last_close_krw": 106300.0,
    "last_close_native": 106700.0,
    "market_value_krw": 22641900.0,
    "qty": 213,
    "symbol": "356860.KQ",
    "unrealized_pnl_krw": -14718.9331,
    "unrealized_return": -0.0006496529354017566
  },
  {
    "account_id": "pit_score_top10",
    "avg_cost_krw": 117270.6397,
    "company": "Arista Networks",
    "currency": "USD",
    "first_buy_date": "2022-12-01",
    "holding_days": 1278,
    "last_close_krw": 256795.7939,
    "last_close_native": 154.27000427246097,
    "market_value_krw": 22598029.863199998,
    "qty": 88,
    "symbol": "ANET",
    "unrealized_pnl_krw": 12278213.5757,
    "unrealized_return": 1.1897705560141154
  },
  {
    "account_id": "pit_score_top10",
    "avg_cost_krw": 62788.566,
    "company": "이수페타시스",
    "currency": "KRW",
    "first_buy_date": "2025-01-02",
    "holding_days": 515,
    "last_close_krw": 139400.0,
    "last_close_native": 120900.0,
    "market_value_krw": 22582800.0,
    "qty": 162,
    "symbol": "007660.KS",
    "unrealized_pnl_krw": 12411052.3076,
    "unrealized_return": 1.220149445680922
  },
  {
    "account_id": "pit_score_top10",
    "avg_cost_krw": 430791.7018,
    "company": "HD현대일렉트릭",
    "currency": "KRW",
    "first_buy_date": "2024-04-01",
    "holding_days": 791,
    "last_close_krw": 1066000.0,
    "last_close_native": 956000.0,
    "market_value_krw": 22386000.0,
    "qty": 21,
    "symbol": "267260.KS",
    "unrealized_pnl_krw": 13339374.2613,
    "unrealized_return": 1.4745137743969425
  },
  {
    "account_id": "pit_score_top10",
    "avg_cost_krw": 244977.1418,
    "company": "Palantir Technologies Inc.",
    "currency": "USD",
    "first_buy_date": "2026-06-01",
    "holding_days": 0,
    "last_close_krw": 244817.9917,
    "last_close_native": 135.52999877929688,
    "market_value_krw": 21788801.2613,
    "qty": 89,
    "symbol": "PLTR",
    "unrealized_pnl_krw": -14164.355,
    "unrealized_return": -0.0006496528567140336
  },
  {
    "account_id": "pit_score_top3",
    "avg_cost_krw": 77481.4114,
    "company": "이수페타시스",
    "currency": "KRW",
    "first_buy_date": "2025-08-01",
    "holding_days": 304,
    "last_close_krw": 139400.0,
    "last_close_native": 120900.0,
    "market_value_krw": 56875200.0,
    "qty": 408,
    "symbol": "007660.KS",
    "unrealized_pnl_krw": 25262784.1329,
    "unrealized_return": 0.7991412066610857
  },
  {
    "account_id": "pit_score_top3",
    "avg_cost_krw": 2364536.1272,
    "company": "SK하이닉스",
    "currency": "KRW",
    "first_buy_date": "2026-06-01",
    "holding_days": 0,
    "last_close_krw": 2363000.0,
    "last_close_native": 2070000.0,
    "market_value_krw": 56712000.0,
    "qty": 24,
    "symbol": "000660.KS",
    "unrealized_pnl_krw": -36867.0534,
    "unrealized_return": -0.0006496526664699909
  },
  {
    "account_id": "pit_score_top3",
    "avg_cost_krw": 185620.5889,
    "company": "주성엔지니어링",
    "currency": "KRW",
    "first_buy_date": "2026-06-01",
    "holding_days": 0,
    "last_close_krw": 185500.0,
    "last_close_native": 210000.0,
    "market_value_krw": 56577500.0,
    "qty": 305,
    "symbol": "036930.KQ",
    "unrealized_pnl_krw": -36779.6183,
    "unrealized_return": -0.0006496526097380384
  },
  {
    "account_id": "pit_score_top5",
    "avg_cost_krw": 114283.8944,
    "company": "Arista Networks",
    "currency": "USD",
    "first_buy_date": "2022-12-01",
    "holding_days": 1278,
    "last_close_krw": 256795.7939,
    "last_close_native": 154.27000427246097,
    "market_value_krw": 40316939.642299995,
    "qty": 157,
    "symbol": "ANET",
    "unrealized_pnl_krw": 22374368.2241,
    "unrealized_return": 1.2469989778367228
  },
  {
    "account_id": "pit_score_top5",
    "avg_cost_krw": 126081.9094,
    "company": "주성엔지니어링",
    "currency": "KRW",
    "first_buy_date": "2026-05-01",
    "holding_days": 31,
    "last_close_krw": 185500.0,
    "last_close_native": 210000.0,
    "market_value_krw": 40253500.0,
    "qty": 217,
    "symbol": "036930.KQ",
    "unrealized_pnl_krw": 12893725.6494,
    "unrealized_return": 0.47126578969782007
  },
  {
    "account_id": "pit_score_top5",
    "avg_cost_krw": 74781.5763,
    "company": "이수페타시스",
    "currency": "KRW",
    "first_buy_date": "2025-07-01",
    "holding_days": 335,
    "last_close_krw": 139400.0,
    "last_close_native": 120900.0,
    "market_value_krw": 40147200.0,
    "qty": 288,
    "symbol": "007660.KS",
    "unrealized_pnl_krw": 18610106.0289,
    "unrealized_return": 0.8640955018221512
  },
  {
    "account_id": "pit_score_top5",
    "avg_cost_krw": 935211.6103,
    "company": "HD현대일렉트릭",
    "currency": "KRW",
    "first_buy_date": "2025-11-03",
    "holding_days": 210,
    "last_close_krw": 1066000.0,
    "last_close_native": 956000.0,
    "market_value_krw": 39442000.0,
    "qty": 37,
    "symbol": "267260.KS",
    "unrealized_pnl_krw": 4839170.4176,
    "unrealized_return": 0.13984897990952594
  },
  {
    "account_id": "pit_score_top5",
    "avg_cost_krw": 2364536.1272,
    "company": "SK하이닉스",
    "currency": "KRW",
    "first_buy_date": "2026-06-01",
    "holding_days": 0,
    "last_close_krw": 2363000.0,
    "last_close_native": 2070000.0,
    "market_value_krw": 37808000.0,
    "qty": 16,
    "symbol": "000660.KS",
    "unrealized_pnl_krw": -24578.0356,
    "unrealized_return": -0.0006496526664699909
  },
  {
    "account_id": "pit_trend_quarterly_fresh540_runwinners_weeklycap45_profit60_candidate_top5",
    "avg_cost_krw": 72146.8704,
    "company": "티엘비",
    "currency": "KRW",
    "first_buy_date": "2026-04-01",
    "holding_days": 61,
    "last_close_krw": 106300.0,
    "last_close_native": 106700.0,
    "market_value_krw": 57402000.0,
    "qty": 540,
    "symbol": "356860.KQ",
    "unrealized_pnl_krw": 18442689.98,
    "unrealized_return": 0.47338338323820084
  },
  {
    "account_id": "pit_trend_quarterly_fresh540_runwinners_weeklycap45_profit60_candidate_top5",
    "avg_cost_krw": 134197.7378,
    "company": "Corning",
    "currency": "USD",
    "first_buy_date": "2026-01-02",
    "holding_days": 150,
    "last_close_krw": 265025.7934,
    "last_close_native": 177.5800018310547,
    "market_value_krw": 47969668.6054,
    "qty": 181,
    "symbol": "GLW",
    "unrealized_pnl_krw": 23679878.0664,
    "unrealized_return": 0.9748901713602509
  },
  {
    "account_id": "pit_trend_quarterly_fresh540_runwinners_weeklycap45_profit60_candidate_top5",
    "avg_cost_krw": 557766.1792,
    "company": "Lumentum Holdings Inc",
    "currency": "USD",
    "first_buy_date": "2026-01-02",
    "holding_days": 150,
    "last_close_krw": 1344995.9815,
    "last_close_native": 863.6599731445312,
    "market_value_krw": 45729863.371,
    "qty": 34,
    "symbol": "LITE",
    "unrealized_pnl_krw": 26765813.2786,
    "unrealized_return": 1.4113975204253473
  },
  {
    "account_id": "pit_trend_quarterly_fresh540_runwinners_weeklycap45_profit60_candidate_top5",
    "avg_cost_krw": 35072.7851,
    "company": "RFHIC",
    "currency": "KRW",
    "first_buy_date": "2026-01-02",
    "holding_days": 150,
    "last_close_krw": 87600.0,
    "last_close_native": 82800.0,
    "market_value_krw": 36266400.0,
    "qty": 414,
    "symbol": "218410.KQ",
    "unrealized_pnl_krw": 21746266.9567,
    "unrealized_return": 1.4976630669686966
  },
  {
    "account_id": "pit_trend_quarterly_fresh540_runwinners_weeklycap45_profit60_candidate_top5",
    "avg_cost_krw": 57737.5093,
    "company": "토모큐브",
    "currency": "KRW",
    "first_buy_date": "2026-04-01",
    "holding_days": 61,
    "last_close_krw": 42150.0,
    "last_close_native": 39850.0,
    "market_value_krw": 28451250.0,
    "qty": 675,
    "symbol": "475960.KQ",
    "unrealized_pnl_krw": -10521568.7961,
    "unrealized_return": -0.2699719729683594
  },
  {
    "account_id": "pit_trend_quarterly_fresh540_runwinners_weeklycap45_profit60_mixedentry_top5",
    "avg_cost_krw": 72146.8704,
    "company": "티엘비",
    "currency": "KRW",
    "first_buy_date": "2026-04-01",
    "holding_days": 61,
    "last_close_krw": 106300.0,
    "last_close_native": 106700.0,
    "market_value_krw": 57402000.0,
    "qty": 540,
    "symbol": "356860.KQ",
    "unrealized_pnl_krw": 18442689.98,
    "unrealized_return": 0.47338338323820084
  },
  {
    "account_id": "pit_trend_quarterly_fresh540_runwinners_weeklycap45_profit60_mixedentry_top5",
    "avg_cost_krw": 134197.7378,
    "company": "Corning",
    "currency": "USD",
    "first_buy_date": "2026-01-02",
    "holding_days": 150,
    "last_close_krw": 265025.7934,
    "last_close_native": 177.5800018310547,
    "market_value_krw": 47969668.6054,
    "qty": 181,
    "symbol": "GLW",
    "unrealized_pnl_krw": 23679878.0664,
    "unrealized_return": 0.9748901713602509
  },
  {
    "account_id": "pit_trend_quarterly_fresh540_runwinners_weeklycap45_profit60_mixedentry_top5",
    "avg_cost_krw": 557766.1792,
    "company": "Lumentum Holdings Inc",
    "currency": "USD",
    "first_buy_date": "2026-01-02",
    "holding_days": 150,
    "last_close_krw": 1344995.9815,
    "last_close_native": 863.6599731445312,
    "market_value_krw": 45729863.371,
    "qty": 34,
    "symbol": "LITE",
    "unrealized_pnl_krw": 26765813.2786,
    "unrealized_return": 1.4113975204253473
  },
  {
    "account_id": "pit_trend_quarterly_fresh540_runwinners_weeklycap45_profit60_mixedentry_top5",
    "avg_cost_krw": 35072.7851,
    "company": "RFHIC",
    "currency": "KRW",
    "first_buy_date": "2026-01-02",
    "holding_days": 150,
    "last_close_krw": 87600.0,
    "last_close_native": 82800.0,
    "market_value_krw": 36266400.0,
    "qty": 414,
    "symbol": "218410.KQ",
    "unrealized_pnl_krw": 21746266.9567,
    "unrealized_return": 1.4976630669686966
  },
  {
    "account_id": "pit_trend_quarterly_fresh540_runwinners_weeklycap45_profit60_mixedentry_top5",
    "avg_cost_krw": 57737.5093,
    "company": "토모큐브",
    "currency": "KRW",
    "first_buy_date": "2026-04-01",
    "holding_days": 61,
    "last_close_krw": 42150.0,
    "last_close_native": 39850.0,
    "market_value_krw": 28451250.0,
    "qty": 675,
    "symbol": "475960.KQ",
    "unrealized_pnl_krw": -10521568.7961,
    "unrealized_return": -0.2699719729683594
  },
  {
    "account_id": "pit_trend_quarterly_fresh540_runwinners_weeklycap45_profit60_mixedentry_trailtrim25cap20_redeploycash125_partial75_top5",
    "avg_cost_krw": 72146.8704,
    "company": "티엘비",
    "currency": "KRW",
    "first_buy_date": "2026-04-01",
    "holding_days": 61,
    "last_close_krw": 106300.0,
    "last_close_native": 106700.0,
    "market_value_krw": 57189400.0,
    "qty": 538,
    "symbol": "356860.KQ",
    "unrealized_pnl_krw": 18374383.7208,
    "unrealized_return": 0.47338338323820084
  },
  {
    "account_id": "pit_trend_quarterly_fresh540_runwinners_weeklycap45_profit60_mixedentry_trailtrim25cap20_redeploycash125_partial75_top5",
    "avg_cost_krw": 133768.8678,
    "company": "Corning",
    "currency": "USD",
    "first_buy_date": "2026-01-02",
    "holding_days": 150,
    "last_close_krw": 265025.7934,
    "last_close_native": 177.5800018310547,
    "market_value_krw": 47439617.0186,
    "qty": 179,
    "symbol": "GLW",
    "unrealized_pnl_krw": 23494989.6798,
    "unrealized_return": 0.9812217727389632
  },
  {
    "account_id": "pit_trend_quarterly_fresh540_runwinners_weeklycap45_profit60_mixedentry_trailtrim25cap20_redeploycash125_partial75_top5",
    "avg_cost_krw": 557766.1792,
    "company": "Lumentum Holdings Inc",
    "currency": "USD",
    "first_buy_date": "2026-01-02",
    "holding_days": 150,
    "last_close_krw": 1344995.9815,
    "last_close_native": 863.6599731445312,
    "market_value_krw": 45729863.371,
    "qty": 34,
    "symbol": "LITE",
    "unrealized_pnl_krw": 26765813.2786,
    "unrealized_return": 1.4113975204253473
  },
  {
    "account_id": "pit_trend_quarterly_fresh540_runwinners_weeklycap45_profit60_mixedentry_trailtrim25cap20_redeploycash125_partial75_top5",
    "avg_cost_krw": 35072.7851,
    "company": "RFHIC",
    "currency": "KRW",
    "first_buy_date": "2026-01-02",
    "holding_days": 150,
    "last_close_krw": 87600.0,
    "last_close_native": 82800.0,
    "market_value_krw": 36178800.0,
    "qty": 413,
    "symbol": "218410.KQ",
    "unrealized_pnl_krw": 21693739.7418,
    "unrealized_return": 1.4976630669686966
  },
  {
    "account_id": "pit_trend_quarterly_fresh540_runwinners_weeklycap45_profit60_mixedentry_trailtrim25cap20_redeploycash125_partial75_top5",
    "avg_cost_krw": 57737.5093,
    "company": "토모큐브",
    "currency": "KRW",
    "first_buy_date": "2026-04-01",
    "holding_days": 61,
    "last_close_krw": 42150.0,
    "last_close_native": 39850.0,
    "market_value_krw": 28324800.0,
    "qty": 672,
    "symbol": "475960.KQ",
    "unrealized_pnl_krw": -10474806.2681,
    "unrealized_return": -0.2699719729683594
  },
  {
    "account_id": "pit_trend_quarterly_fresh540_runwinners_weeklycap45_profit60_mixedentry_trailtrim25cap20_redeploycash125_top5",
    "avg_cost_krw": 72146.8704,
    "company": "티엘비",
    "currency": "KRW",
    "first_buy_date": "2026-04-01",
    "holding_days": 61,
    "last_close_krw": 106300.0,
    "last_close_native": 106700.0,
    "market_value_krw": 57189400.0,
    "qty": 538,
    "symbol": "356860.KQ",
    "unrealized_pnl_krw": 18374383.7208,
    "unrealized_return": 0.47338338323820084
  },
  {
    "account_id": "pit_trend_quarterly_fresh540_runwinners_weeklycap45_profit60_mixedentry_trailtrim25cap20_redeploycash125_top5",
    "avg_cost_krw": 133768.8678,
    "company": "Corning",
    "currency": "USD",
    "first_buy_date": "2026-01-02",
    "holding_days": 150,
    "last_close_krw": 265025.7934,
    "last_close_native": 177.5800018310547,
    "market_value_krw": 47439617.0186,
    "qty": 179,
    "symbol": "GLW",
    "unrealized_pnl_krw": 23494989.6798,
    "unrealized_return": 0.9812217727389632
  },
  {
    "account_id": "pit_trend_quarterly_fresh540_runwinners_weeklycap45_profit60_mixedentry_trailtrim25cap20_redeploycash125_top5",
    "avg_cost_krw": 557766.1792,
    "company": "Lumentum Holdings Inc",
    "currency": "USD",
    "first_buy_date": "2026-01-02",
    "holding_days": 150,
    "last_close_krw": 1344995.9815,
    "last_close_native": 863.6599731445312,
    "market_value_krw": 45729863.371,
    "qty": 34,
    "symbol": "LITE",
    "unrealized_pnl_krw": 26765813.2786,
    "unrealized_return": 1.4113975204253473
  },
  {
    "account_id": "pit_trend_quarterly_fresh540_runwinners_weeklycap45_profit60_mixedentry_trailtrim25cap20_redeploycash125_top5",
    "avg_cost_krw": 35072.7851,
    "company": "RFHIC",
    "currency": "KRW",
    "first_buy_date": "2026-01-02",
    "holding_days": 150,
    "last_close_krw": 87600.0,
    "last_close_native": 82800.0,
    "market_value_krw": 36178800.0,
    "qty": 413,
    "symbol": "218410.KQ",
    "unrealized_pnl_krw": 21693739.7418,
    "unrealized_return": 1.4976630669686966
  },
  {
    "account_id": "pit_trend_quarterly_fresh540_runwinners_weeklycap45_profit60_mixedentry_trailtrim25cap20_redeploycash125_top5",
    "avg_cost_krw": 57737.5093,
    "company": "토모큐브",
    "currency": "KRW",
    "first_buy_date": "2026-04-01",
    "holding_days": 61,
    "last_close_krw": 42150.0,
    "last_close_native": 39850.0,
    "market_value_krw": 28324800.0,
    "qty": 672,
    "symbol": "475960.KQ",
    "unrealized_pnl_krw": -10474806.2681,
    "unrealized_return": -0.2699719729683594
  },
  {
    "account_id": "pit_trend_quarterly_fresh540_runwinners_weeklycap45_profit60_mixedentry_trailtrim25cap20_top5",
    "avg_cost_krw": 72146.8704,
    "company": "티엘비",
    "currency": "KRW",
    "first_buy_date": "2026-04-01",
    "holding_days": 61,
    "last_close_krw": 106300.0,
    "last_close_native": 106700.0,
    "market_value_krw": 57189400.0,
    "qty": 538,
    "symbol": "356860.KQ",
    "unrealized_pnl_krw": 18374383.7208,
    "unrealized_return": 0.47338338323820084
  },
  {
    "account_id": "pit_trend_quarterly_fresh540_runwinners_weeklycap45_profit60_mixedentry_trailtrim25cap20_top5",
    "avg_cost_krw": 133768.8678,
    "company": "Corning",
    "currency": "USD",
    "first_buy_date": "2026-01-02",
    "holding_days": 150,
    "last_close_krw": 265025.7934,
    "last_close_native": 177.5800018310547,
    "market_value_krw": 47439617.0186,
    "qty": 179,
    "symbol": "GLW",
    "unrealized_pnl_krw": 23494989.6798,
    "unrealized_return": 0.9812217727389632
  },
  {
    "account_id": "pit_trend_quarterly_fresh540_runwinners_weeklycap45_profit60_mixedentry_trailtrim25cap20_top5",
    "avg_cost_krw": 557766.1792,
    "company": "Lumentum Holdings Inc",
    "currency": "USD",
    "first_buy_date": "2026-01-02",
    "holding_days": 150,
    "last_close_krw": 1344995.9815,
    "last_close_native": 863.6599731445312,
    "market_value_krw": 45729863.371,
    "qty": 34,
    "symbol": "LITE",
    "unrealized_pnl_krw": 26765813.2786,
    "unrealized_return": 1.4113975204253473
  },
  {
    "account_id": "pit_trend_quarterly_fresh540_runwinners_weeklycap45_profit60_mixedentry_trailtrim25cap20_top5",
    "avg_cost_krw": 35072.7851,
    "company": "RFHIC",
    "currency": "KRW",
    "first_buy_date": "2026-01-02",
    "holding_days": 150,
    "last_close_krw": 87600.0,
    "last_close_native": 82800.0,
    "market_value_krw": 36178800.0,
    "qty": 413,
    "symbol": "218410.KQ",
    "unrealized_pnl_krw": 21693739.7418,
    "unrealized_return": 1.4976630669686966
  },
  {
    "account_id": "pit_trend_quarterly_fresh540_runwinners_weeklycap45_profit60_mixedentry_trailtrim25cap20_top5",
    "avg_cost_krw": 57737.5093,
    "company": "토모큐브",
    "currency": "KRW",
    "first_buy_date": "2026-04-01",
    "holding_days": 61,
    "last_close_krw": 42150.0,
    "last_close_native": 39850.0,
    "market_value_krw": 28324800.0,
    "qty": 672,
    "symbol": "475960.KQ",
    "unrealized_pnl_krw": -10474806.2681,
    "unrealized_return": -0.2699719729683594
  },
  {
    "account_id": "pit_trend_quarterly_fresh540_runwinners_weeklycap45_profit60_top5",
    "avg_cost_krw": 72146.8704,
    "company": "티엘비",
    "currency": "KRW",
    "first_buy_date": "2026-04-01",
    "holding_days": 61,
    "last_close_krw": 106300.0,
    "last_close_native": 106700.0,
    "market_value_krw": 64949300.0,
    "qty": 611,
    "symbol": "356860.KQ",
    "unrealized_pnl_krw": 20867562.181,
    "unrealized_return": 0.47338338323820084
  },
  {
    "account_id": "pit_trend_quarterly_fresh540_runwinners_weeklycap45_profit60_top5",
    "avg_cost_krw": 133039.4176,
    "company": "Corning",
    "currency": "USD",
    "first_buy_date": "2026-01-02",
    "holding_days": 150,
    "last_close_krw": 265025.7934,
    "last_close_native": 177.5800018310547,
    "market_value_krw": 53535210.2668,
    "qty": 202,
    "symbol": "GLW",
    "unrealized_pnl_krw": 26661247.904,
    "unrealized_return": 0.9920847383505087
  },
  {
    "account_id": "pit_trend_quarterly_fresh540_runwinners_weeklycap45_profit60_top5",
    "avg_cost_krw": 557766.1792,
    "company": "Lumentum Holdings Inc",
    "currency": "USD",
    "first_buy_date": "2026-01-02",
    "holding_days": 150,
    "last_close_krw": 1344995.9815,
    "last_close_native": 863.6599731445312,
    "market_value_krw": 52454843.2785,
    "qty": 39,
    "symbol": "LITE",
    "unrealized_pnl_krw": 30701962.2901,
    "unrealized_return": 1.4113975204253473
  },
  {
    "account_id": "pit_trend_quarterly_fresh540_runwinners_weeklycap45_profit60_top5",
    "avg_cost_krw": 35072.7851,
    "company": "RFHIC",
    "currency": "KRW",
    "first_buy_date": "2026-01-02",
    "holding_days": 150,
    "last_close_krw": 87600.0,
    "last_close_native": 82800.0,
    "market_value_krw": 41084400.0,
    "qty": 469,
    "symbol": "218410.KQ",
    "unrealized_pnl_krw": 24635263.7746,
    "unrealized_return": 1.4976630669686966
  },
  {
    "account_id": "pit_trend_quarterly_fresh540_runwinners_weeklycap45_profit60_top5",
    "avg_cost_krw": 57737.5093,
    "company": "토모큐브",
    "currency": "KRW",
    "first_buy_date": "2026-04-01",
    "holding_days": 61,
    "last_close_krw": 42150.0,
    "last_close_native": 39850.0,
    "market_value_krw": 32202600.0,
    "qty": 764,
    "symbol": "475960.KQ",
    "unrealized_pnl_krw": -11908857.1262,
    "unrealized_return": -0.2699719729683594
  },
  {
    "account_id": "pit_trend_top5",
    "avg_cost_krw": 60639.3945,
    "company": "티엘비",
    "currency": "KRW",
    "first_buy_date": "2026-03-02",
    "holding_days": 91,
    "last_close_krw": 106300.0,
    "last_close_native": 106700.0,
    "market_value_krw": 62291800.0,
    "qty": 586,
    "symbol": "356860.KQ",
    "unrealized_pnl_krw": 26757114.7966,
    "unrealized_return": 0.7529858415720163
  },
  {
    "account_id": "pit_trend_top5",
    "avg_cost_krw": 97876.9148,
    "company": "Aixtron SE",
    "currency": "EUR",
    "first_buy_date": "2026-06-01",
    "holding_days": 0,
    "last_close_krw": 97813.3288,
    "last_close_native": 54.639999389648445,
    "market_value_krw": 62111463.788,
    "qty": 635,
    "symbol": "AIXA.DE",
    "unrealized_pnl_krw": -40377.1098,
    "unrealized_return": -0.0006496526798982494
  },
  {
    "account_id": "pit_trend_top5",
    "avg_cost_krw": 402761.6552,
    "company": "로보티즈",
    "currency": "KRW",
    "first_buy_date": "2026-06-01",
    "holding_days": 0,
    "last_close_krw": 402500.0,
    "last_close_native": 320500.0,
    "market_value_krw": 61985000.0,
    "qty": 154,
    "symbol": "108490.KQ",
    "unrealized_pnl_krw": -40294.8989,
    "unrealized_return": -0.0006496527080515069
  },
  {
    "account_id": "pit_trend_top5",
    "avg_cost_krw": 2204432.1152,
    "company": "두산",
    "currency": "KRW",
    "first_buy_date": "2026-06-01",
    "holding_days": 0,
    "last_close_krw": 2203000.0,
    "last_close_native": 1740000.0,
    "market_value_krw": 61684000.0,
    "qty": 28,
    "symbol": "000150.KS",
    "unrealized_pnl_krw": -40099.2263,
    "unrealized_return": -0.0006496526657024937
  },
  {
    "account_id": "pit_trend_top5",
    "avg_cost_krw": 761494.7071,
    "company": "현대모비스",
    "currency": "KRW",
    "first_buy_date": "2026-06-01",
    "holding_days": 0,
    "last_close_krw": 761000.0,
    "last_close_native": 697000.0,
    "market_value_krw": 61641000.0,
    "qty": 81,
    "symbol": "012330.KS",
    "unrealized_pnl_krw": -40071.2731,
    "unrealized_return": -0.0006496527098448501
  },
  {
    "account_id": "smic_follower",
    "avg_cost_krw": 8600.3401,
    "company": "JAC recruitment Co. Ltd",
    "currency": "JPY",
    "first_buy_date": "2025-12-01",
    "holding_days": 182,
    "last_close_krw": 8176.0323,
    "last_close_native": 860.0,
    "market_value_krw": 11495501.4138,
    "qty": 1406,
    "symbol": "2124.T",
    "unrealized_pnl_krw": -596576.7887,
    "unrealized_return": -0.04933616520583872
  },
  {
    "account_id": "smic_follower",
    "avg_cost_krw": 123371.2825,
    "company": "Coreweave",
    "currency": "USD",
    "first_buy_date": "2025-12-05",
    "holding_days": 178,
    "last_close_krw": 188555.6513,
    "last_close_native": 100.38999938964844,
    "market_value_krw": 7165114.7494,
    "qty": 38,
    "symbol": "CRWV",
    "unrealized_pnl_krw": 2477006.0175,
    "unrealized_return": 0.5283593351637565
  },
  {
    "account_id": "smic_follower",
    "avg_cost_krw": 5956.4987,
    "company": "Funko Inc.",
    "currency": "USD",
    "first_buy_date": "2024-11-25",
    "holding_days": 553,
    "last_close_krw": 8434.4285,
    "last_close_native": 5.099999904632568,
    "market_value_krw": 6553550.9445,
    "qty": 777,
    "symbol": "FNKO",
    "unrealized_pnl_krw": 1925351.4462,
    "unrealized_return": 0.4160044221952066
  },
  {
    "account_id": "smic_follower",
    "avg_cost_krw": 19369.1006,
    "company": "예스티",
    "currency": "KRW",
    "first_buy_date": "2026-01-06",
    "holding_days": 146,
    "last_close_krw": 26400.0,
    "last_close_native": 25550.0,
    "market_value_krw": 5306400.0,
    "qty": 201,
    "symbol": "122640.KQ",
    "unrealized_pnl_krw": 1413210.7792,
    "unrealized_return": 0.36299565711378445
  },
  {
    "account_id": "smic_follower",
    "avg_cost_krw": 22307.2665,
    "company": "마이크로컨텍솔",
    "currency": "KRW",
    "first_buy_date": "2025-11-03",
    "holding_days": 210,
    "last_close_krw": 29700.0,
    "last_close_native": 27500.0,
    "market_value_krw": 5138100.0,
    "qty": 173,
    "symbol": "098120.KQ",
    "unrealized_pnl_krw": 1278942.8883,
    "unrealized_return": 0.3314047241063802
  },
  {
    "account_id": "smic_follower",
    "avg_cost_krw": 21942.3505,
    "company": "Cellebrite DI",
    "currency": "USD",
    "first_buy_date": "2025-06-02",
    "holding_days": 364,
    "last_close_krw": 24091.8765,
    "last_close_native": 13.8100004196167,
    "market_value_krw": 4938834.6825,
    "qty": 205,
    "symbol": "CLBT",
    "unrealized_pnl_krw": 440652.825,
    "unrealized_return": 0.09796243114428416
  },
  {
    "account_id": "smic_follower",
    "avg_cost_krw": 55941.415,
    "company": "한화비전",
    "currency": "KRW",
    "first_buy_date": "2025-05-12",
    "holding_days": 385,
    "last_close_krw": 70800.0,
    "last_close_native": 71500.0,
    "market_value_krw": 4885200.0,
    "qty": 69,
    "symbol": "489790.KS",
    "unrealized_pnl_krw": 1025242.3682,
    "unrealized_return": 0.26560974548105376
  },
  {
    "account_id": "smic_follower",
    "avg_cost_krw": 18718.1283,
    "company": "Cover Corp",
    "currency": "JPY",
    "first_buy_date": "2024-11-25",
    "holding_days": 553,
    "last_close_krw": 15453.0795,
    "last_close_native": 1630.0,
    "market_value_krw": 4821360.804,
    "qty": 312,
    "symbol": "5253.T",
    "unrealized_pnl_krw": -1018695.2439,
    "unrealized_return": -0.17443244044865325
  },
  {
    "account_id": "smic_follower",
    "avg_cost_krw": 101428.4935,
    "company": "Establishment Labs Holdings",
    "currency": "USD",
    "first_buy_date": "2025-12-05",
    "holding_days": 178,
    "last_close_krw": 106316.1939,
    "last_close_native": 74.30999755859375,
    "market_value_krw": 4784228.7255,
    "qty": 45,
    "symbol": "ESTA",
    "unrealized_pnl_krw": 219946.5176,
    "unrealized_return": 0.04818863251675931
  },
  {
    "account_id": "smic_follower",
    "avg_cost_krw": 27044.2596,
    "company": "Levi Strauss & Co",
    "currency": "USD",
    "first_buy_date": "2025-01-15",
    "holding_days": 502,
    "last_close_krw": 34926.4079,
    "last_close_native": 22.530000686645508,
    "market_value_krw": 4575359.4349,
    "qty": 131,
    "symbol": "LEVI",
    "unrealized_pnl_krw": 1032561.428,
    "unrealized_return": 0.2914536547341824
  },
  {
    "account_id": "smic_follower",
    "avg_cost_krw": 10426.2203,
    "company": "고려신용정보",
    "currency": "KRW",
    "first_buy_date": "2025-06-25",
    "holding_days": 341,
    "last_close_krw": 9500.0,
    "last_close_native": 9760.0,
    "market_value_krw": 4294000.0,
    "qty": 452,
    "symbol": "049720.KQ",
    "unrealized_pnl_krw": -418651.5867,
    "unrealized_return": -0.08883567326886432
  },
  {
    "account_id": "smic_follower",
    "avg_cost_krw": 293455.3499,
    "company": "크래프톤",
    "currency": "KRW",
    "first_buy_date": "2024-11-25",
    "holding_days": 553,
    "last_close_krw": 249500.0,
    "last_close_native": 257500.0,
    "market_value_krw": 4241500.0,
    "qty": 17,
    "symbol": "259960.KQ",
    "unrealized_pnl_krw": -747240.9489,
    "unrealized_return": -0.14978547814847654
  },
  {
    "account_id": "smic_follower",
    "avg_cost_krw": 5923.1858,
    "company": "KG스틸",
    "currency": "KRW",
    "first_buy_date": "2024-06-07",
    "holding_days": 724,
    "last_close_krw": 5610.0,
    "last_close_native": 5340.0,
    "market_value_krw": 4235550.0,
    "qty": 755,
    "symbol": "016380.KS",
    "unrealized_pnl_krw": -236455.2502,
    "unrealized_return": -0.05287455274490971
  },
  {
    "account_id": "smic_follower",
    "avg_cost_krw": 68195.6548,
    "company": "JYP Ent.",
    "currency": "KRW",
    "first_buy_date": "2024-12-09",
    "holding_days": 539,
    "last_close_krw": 56500.0,
    "last_close_native": 53200.0,
    "market_value_krw": 4181000.0,
    "qty": 74,
    "symbol": "035900.KQ",
    "unrealized_pnl_krw": -865478.4582,
    "unrealized_return": -0.1715014663954807
  },
  {
    "account_id": "smic_follower",
    "avg_cost_krw": 52250.7925,
    "company": "IMAX Corp",
    "currency": "USD",
    "first_buy_date": "2025-12-05",
    "holding_days": 178,
    "last_close_krw": 60933.9755,
    "last_close_native": 38.970001220703125,
    "market_value_krw": 4143510.334,
    "qty": 68,
    "symbol": "IMAX",
    "unrealized_pnl_krw": 590456.4434,
    "unrealized_return": 0.16618280000250718
  },
  {
    "account_id": "smic_follower",
    "avg_cost_krw": 42925.614,
    "company": "씨에스윈드",
    "currency": "KRW",
    "first_buy_date": "2024-11-01",
    "holding_days": 577,
    "last_close_krw": 46750.0,
    "last_close_native": 43850.0,
    "market_value_krw": 4114000.0,
    "qty": 88,
    "symbol": "112610.KS",
    "unrealized_pnl_krw": 336545.9669,
    "unrealized_return": 0.08909333247976359
  },
  {
    "account_id": "smic_follower",
    "avg_cost_krw": 73025.7546,
    "company": "아프리카TV",
    "currency": "KRW",
    "first_buy_date": "2024-11-01",
    "holding_days": 577,
    "last_close_krw": 49550.0,
    "last_close_native": 48250.0,
    "market_value_krw": 4112650.0,
    "qty": 83,
    "symbol": "067160.KQ",
    "unrealized_pnl_krw": -1948487.6343,
    "unrealized_return": -0.32147226315686717
  },
  {
    "account_id": "smic_follower",
    "avg_cost_krw": 56416.3979,
    "company": "비츠로셀",
    "currency": "KRW",
    "first_buy_date": "2026-04-17",
    "holding_days": 45,
    "last_close_krw": 52000.0,
    "last_close_native": 48650.0,
    "market_value_krw": 4108000.0,
    "qty": 79,
    "symbol": "082920.KS",
    "unrealized_pnl_krw": -348895.434,
    "unrealized_return": -0.07828216732000903
  },
  {
    "account_id": "smic_follower",
    "avg_cost_krw": 412460.2636,
    "company": "파마리서치",
    "currency": "KRW",
    "first_buy_date": "2026-01-09",
    "holding_days": 143,
    "last_close_krw": 298000.0,
    "last_close_native": 286500.0,
    "market_value_krw": 3874000.0,
    "qty": 13,
    "symbol": "214450.KQ",
    "unrealized_pnl_krw": -1487983.4269,
    "unrealized_return": -0.27750615926241673
  },
  {
    "account_id": "smic_follower",
    "avg_cost_krw": 136213.846,
    "company": "Sensient Technologies Corp",
    "currency": "USD",
    "first_buy_date": "2026-01-28",
    "holding_days": 124,
    "last_close_krw": 167212.1662,
    "last_close_native": 112.19000244140625,
    "market_value_krw": 3845879.8226,
    "qty": 23,
    "symbol": "SXT",
    "unrealized_pnl_krw": 712961.3657,
    "unrealized_return": 0.2275709930398706
  },
  {
    "account_id": "smic_follower",
    "avg_cost_krw": 20472.2582,
    "company": "HDC현대산업개발",
    "currency": "KRW",
    "first_buy_date": "2024-11-25",
    "holding_days": 553,
    "last_close_krw": 19920.0,
    "last_close_native": 19510.0,
    "market_value_krw": 3824640.0,
    "qty": 192,
    "symbol": "294870.KS",
    "unrealized_pnl_krw": -106033.5726,
    "unrealized_return": -0.026975929797524723
  },
  {
    "account_id": "smic_follower",
    "avg_cost_krw": 54660.0168,
    "company": "Doximity",
    "currency": "USD",
    "first_buy_date": "2025-06-04",
    "holding_days": 362,
    "last_close_krw": 33813.4259,
    "last_close_native": 20.590000152587887,
    "market_value_krw": 3787103.7008,
    "qty": 112,
    "symbol": "DOCS",
    "unrealized_pnl_krw": -2334818.1853,
    "unrealized_return": -0.3813864707776672
  },
  {
    "account_id": "smic_follower",
    "avg_cost_krw": 144171.0023,
    "company": "Iradimed Corporation",
    "currency": "USD",
    "first_buy_date": "2025-12-05",
    "holding_days": 178,
    "last_close_krw": 138251.9435,
    "last_close_native": 93.06999969482422,
    "market_value_krw": 3732802.4745,
    "qty": 27,
    "symbol": "IRMD",
    "unrealized_pnl_krw": -159814.5885,
    "unrealized_return": -0.041055820557335476
  },
  {
    "account_id": "smic_follower",
    "avg_cost_krw": 3832.5259,
    "company": "에스트래픽",
    "currency": "KRW",
    "first_buy_date": "2024-11-25",
    "holding_days": 553,
    "last_close_krw": 2980.0,
    "last_close_native": 2965.0,
    "market_value_krw": 3719040.0,
    "qty": 1248,
    "symbol": "234300.KQ",
    "unrealized_pnl_krw": -1063952.2837,
    "unrealized_return": -0.22244491550598522
  },
  {
    "account_id": "smic_follower",
    "avg_cost_krw": 23216.6655,
    "company": "브이티",
    "currency": "KRW",
    "first_buy_date": "2024-11-12",
    "holding_days": 566,
    "last_close_krw": 13000.0,
    "last_close_native": 12320.0,
    "market_value_krw": 3614000.0,
    "qty": 278,
    "symbol": "018290.KS",
    "unrealized_pnl_krw": -2840233.0098,
    "unrealized_return": -0.4400574018693597
  },
  {
    "account_id": "smic_follower",
    "avg_cost_krw": 31582.4224,
    "company": "한국카본",
    "currency": "KRW",
    "first_buy_date": "2025-11-11",
    "holding_days": 202,
    "last_close_krw": 32150.0,
    "last_close_native": 32250.0,
    "market_value_krw": 3375750.0,
    "qty": 105,
    "symbol": "017960.KS",
    "unrealized_pnl_krw": 59595.6514,
    "unrealized_return": 0.01797131305545463
  },
  {
    "account_id": "smic_follower",
    "avg_cost_krw": 47636.5027,
    "company": "덕산네오룩스",
    "currency": "KRW",
    "first_buy_date": "2026-05-11",
    "holding_days": 21,
    "last_close_krw": 37050.0,
    "last_close_native": 34700.0,
    "market_value_krw": 3334500.0,
    "qty": 90,
    "symbol": "213420.KS",
    "unrealized_pnl_krw": -952785.2463,
    "unrealized_return": -0.22223509493697569
  },
  {
    "account_id": "smic_follower",
    "avg_cost_krw": 6277.6426,
    "company": "나노",
    "currency": "KRW",
    "first_buy_date": "2026-05-11",
    "holding_days": 21,
    "last_close_krw": 5500.0,
    "last_close_native": 5590.0,
    "market_value_krw": 3333000.0,
    "qty": 606,
    "symbol": "187790.KS",
    "unrealized_pnl_krw": -471251.4421,
    "unrealized_return": -0.12387493993366239
  },
  {
    "account_id": "smic_follower",
    "avg_cost_krw": 23069.4821,
    "company": "SK오션플랜트",
    "currency": "KRW",
    "first_buy_date": "2026-04-17",
    "holding_days": 45,
    "last_close_krw": 16820.0,
    "last_close_native": 15780.0,
    "market_value_krw": 3330360.0,
    "qty": 198,
    "symbol": "100090.KS",
    "unrealized_pnl_krw": -1237397.4559,
    "unrealized_return": -0.270898240060621
  },
  {
    "account_id": "smic_follower",
    "avg_cost_krw": 5671.696,
    "company": "폰드그룹",
    "currency": "KRW",
    "first_buy_date": "2025-07-16",
    "holding_days": 320,
    "last_close_krw": 4215.0,
    "last_close_native": 4230.0,
    "market_value_krw": 3325635.0,
    "qty": 789,
    "symbol": "472850.KQ",
    "unrealized_pnl_krw": -1149333.1399,
    "unrealized_return": -0.25683605045122304
  },
  {
    "account_id": "smic_follower",
    "avg_cost_krw": 4021.7526,
    "company": "애니플러스",
    "currency": "KRW",
    "first_buy_date": "2025-06-10",
    "holding_days": 356,
    "last_close_krw": 2145.0,
    "last_close_native": 2245.0,
    "market_value_krw": 3266835.0,
    "qty": 1523,
    "symbol": "310200.KQ",
    "unrealized_pnl_krw": -2858294.2066,
    "unrealized_return": -0.466650434937246
  },
  {
    "account_id": "smic_follower",
    "avg_cost_krw": 83924.8924,
    "company": "지투지바이오",
    "currency": "KRW",
    "first_buy_date": "2025-11-11",
    "holding_days": 202,
    "last_close_krw": 56400.0,
    "last_close_native": 53000.0,
    "market_value_krw": 3045600.0,
    "qty": 54,
    "symbol": "456160.KQ",
    "unrealized_pnl_krw": -1486344.1897,
    "unrealized_return": -0.32797054143140014
  },
  {
    "account_id": "smic_follower",
    "avg_cost_krw": 90846.4942,
    "company": "Tempus AI Inc",
    "currency": "USD",
    "first_buy_date": "2026-01-28",
    "holding_days": 124,
    "last_close_krw": 80149.7828,
    "last_close_native": 46.43000030517578,
    "market_value_krw": 2965541.9636,
    "qty": 37,
    "symbol": "TEM",
    "unrealized_pnl_krw": -395778.323,
    "unrealized_return": -0.11774490027596463
  },
  {
    "account_id": "smic_follower",
    "avg_cost_krw": 31274.3613,
    "company": "Sportradar",
    "currency": "USD",
    "first_buy_date": "2025-06-09",
    "holding_days": 357,
    "last_close_krw": 20442.5101,
    "last_close_native": 13.899999618530275,
    "market_value_krw": 2514428.7423,
    "qty": 123,
    "symbol": "SRAD",
    "unrealized_pnl_krw": -1332317.6937,
    "unrealized_return": -0.3463492378339954
  },
  {
    "account_id": "smic_follower",
    "avg_cost_krw": 12801.9532,
    "company": "샘씨엔에스",
    "currency": "KRW",
    "first_buy_date": "2026-05-11",
    "holding_days": 21,
    "last_close_krw": 12670.0,
    "last_close_native": 12830.0,
    "market_value_krw": 2229920.0,
    "qty": 176,
    "symbol": "252990.KQ",
    "unrealized_pnl_krw": -23223.7609,
    "unrealized_return": -0.010307270924877265
  },
  {
    "account_id": "smic_follower_v2",
    "avg_cost_krw": 20000.3851,
    "company": "예스티",
    "currency": "KRW",
    "first_buy_date": "2025-12-17",
    "holding_days": 166,
    "last_close_krw": 26400.0,
    "last_close_native": 25550.0,
    "market_value_krw": 21964800.0,
    "qty": 832,
    "symbol": "122640.KQ",
    "unrealized_pnl_krw": 5324479.5713,
    "unrealized_return": 0.31997458388938727
  },
  {
    "account_id": "smic_follower_v2",
    "avg_cost_krw": 137742.1901,
    "company": "Sensient Technologies Corp",
    "currency": "USD",
    "first_buy_date": "2026-01-09",
    "holding_days": 143,
    "last_close_krw": 167212.1662,
    "last_close_native": 112.19000244140625,
    "market_value_krw": 21904793.7722,
    "qty": 131,
    "symbol": "SXT",
    "unrealized_pnl_krw": 3860566.8652,
    "unrealized_return": 0.21395025067196172
  },
  {
    "account_id": "smic_follower_v2",
    "avg_cost_krw": 19457.47,
    "company": "Cellebrite DI",
    "currency": "USD",
    "first_buy_date": "2025-06-04",
    "holding_days": 362,
    "last_close_krw": 24091.8765,
    "last_close_native": 13.8100004196167,
    "market_value_krw": 21128575.6905,
    "qty": 877,
    "symbol": "CLBT",
    "unrealized_pnl_krw": 4064374.558,
    "unrealized_return": 0.23818135142955366
  },
  {
    "account_id": "smic_follower_v2",
    "avg_cost_krw": 99040.9266,
    "company": "Establishment Labs Holdings",
    "currency": "USD",
    "first_buy_date": "2025-12-02",
    "holding_days": 181,
    "last_close_krw": 106316.1939,
    "last_close_native": 74.30999755859375,
    "market_value_krw": 20519025.4227,
    "qty": 193,
    "symbol": "ESTA",
    "unrealized_pnl_krw": 1404126.5836,
    "unrealized_return": 0.07345718128610468
  },
  {
    "account_id": "smic_follower_v2",
    "avg_cost_krw": 51988.5266,
    "company": "IMAX Corp",
    "currency": "USD",
    "first_buy_date": "2026-01-06",
    "holding_days": 146,
    "last_close_krw": 60933.9755,
    "last_close_native": 38.970001220703125,
    "market_value_krw": 18523928.552,
    "qty": 304,
    "symbol": "IMAX",
    "unrealized_pnl_krw": 2719416.4778,
    "unrealized_return": 0.17206582846300567
  },
  {
    "account_id": "smic_follower_v2",
    "avg_cost_krw": 144409.4826,
    "company": "Iradimed Corporation",
    "currency": "USD",
    "first_buy_date": "2026-01-09",
    "holding_days": 143,
    "last_close_krw": 138251.9435,
    "last_close_native": 93.06999969482422,
    "market_value_krw": 16037225.445999999,
    "qty": 116,
    "symbol": "IRMD",
    "unrealized_pnl_krw": -714274.5328,
    "unrealized_return": -0.04263943744647136
  },
  {
    "account_id": "smic_follower_v2",
    "avg_cost_krw": 10494.5386,
    "company": "고려신용정보",
    "currency": "KRW",
    "first_buy_date": "2025-06-25",
    "holding_days": 341,
    "last_close_krw": 9500.0,
    "last_close_native": 9760.0,
    "market_value_krw": 15922000.0,
    "qty": 1676,
    "symbol": "049720.KQ",
    "unrealized_pnl_krw": -1666846.6413,
    "unrealized_return": -0.09476725351222204
  },
  {
    "account_id": "smic_follower_v2",
    "avg_cost_krw": 32344.7539,
    "company": "한국카본",
    "currency": "KRW",
    "first_buy_date": "2025-11-11",
    "holding_days": 202,
    "last_close_krw": 32150.0,
    "last_close_native": 32250.0,
    "market_value_krw": 13406550.0,
    "qty": 417,
    "symbol": "017960.KS",
    "unrealized_pnl_krw": -81212.3609,
    "unrealized_return": -0.0060211897299363715
  },
  {
    "account_id": "smic_follower_v2",
    "avg_cost_krw": 57037.0543,
    "company": "비츠로셀",
    "currency": "KRW",
    "first_buy_date": "2026-05-06",
    "holding_days": 26,
    "last_close_krw": 52000.0,
    "last_close_native": 48650.0,
    "market_value_krw": 12584000.0,
    "qty": 242,
    "symbol": "082920.KS",
    "unrealized_pnl_krw": -1218967.1345,
    "unrealized_return": -0.0883119642453205
  },
  {
    "account_id": "smic_follower_v2",
    "avg_cost_krw": 23165.0492,
    "company": "SK오션플랜트",
    "currency": "KRW",
    "first_buy_date": "2026-05-06",
    "holding_days": 26,
    "last_close_krw": 16820.0,
    "last_close_native": 15780.0,
    "market_value_krw": 8965060.0,
    "qty": 533,
    "symbol": "100090.KS",
    "unrealized_pnl_krw": -3381911.2429,
    "unrealized_return": -0.27390613959930643
  },
  {
    "account_id": "smic_follower_v2",
    "avg_cost_krw": 5514.4021,
    "company": "나노",
    "currency": "KRW",
    "first_buy_date": "2026-05-07",
    "holding_days": 25,
    "last_close_krw": 5500.0,
    "last_close_native": 5590.0,
    "market_value_krw": 2013000.0,
    "qty": 366,
    "symbol": "187790.KS",
    "unrealized_pnl_krw": -5271.1753,
    "unrealized_return": -0.002611724669116966
  },
  {
    "account_id": "smic_follower_v2",
    "avg_cost_krw": 275258.5633,
    "company": "Camtek",
    "currency": "USD",
    "first_buy_date": "2026-05-01",
    "holding_days": 31,
    "last_close_krw": 250962.0943,
    "last_close_native": 164.2100067138672,
    "market_value_krw": 1756734.6601,
    "qty": 7,
    "symbol": "CAMT",
    "unrealized_pnl_krw": -170075.2829,
    "unrealized_return": -0.0882678043099413
  }
]
